talospider/__init__.py
talospider/downloader.py
talospider/field.py
talospider/item.py
talospider/spider.py
talospider/utils/__init__.py
talospider/utils/function.py
talospider/utils/log.py
talospider/utils/user_agents.txt
talospider-0.0.6.dist-info/DESCRIPTION.rst
talospider-0.0.6.dist-info/METADATA
talospider-0.0.6.dist-info/RECORD
talospider-0.0.6.dist-info/WHEEL
talospider-0.0.6.dist-info/metadata.json
talospider-0.0.6.dist-info/top_level.txt
