Metadata-Version: 2.0
Name: talospider
Version: 0.0.6
Summary: A simple,lightweight scraping micro-framework
Home-page: https://github.com/howie6879/talospider/blob/master/README.md
Author: Howie Hu
Author-email: xiaozizayang@gmail.com
License: UNKNOWN
Platform: UNKNOWN
Requires-Dist: cchardet
Requires-Dist: cssselect
Requires-Dist: lxml
Requires-Dist: requests
